{
    "ZjaP5BbXGm/UNaMG9LI+kw==": {
        "creditValue": 289457.21,
        "paidValue": 24840.21,
        "sellingPrice": 31000,
        "sellingValue": 6159.790000000001,
        "profit": 2.128048563723806,
        "timestamp": 1662685517988,
        "categoriaID": 1,
        "propostaID": "ZjaP5BbXGm/UNaMG9LI+kw==",
        "dataRegistro": "2022-08-20T22:10:48.513",
        "valorPago": 24840.21,
        "valorCredito": 289457.21,
        "valorVenda": 31000,
        "percentualAgioVenda": 10.71,
        "dataExpiracao": "2022-09-27T16:08:33.547",
        "parcelasPagas": 14,
        "parcelasRestantes": 166,
        "valorParcela": 1909.42,
        "saldoDevedor": 316920.85,
        "proximoVencimento": "2022-10-08T00:00:00"
    },
    "0J14ZCxmEoi5aGsmqEtkOw==": {
        "creditValue": 481854.72,
        "paidValue": 107289.2,
        "sellingPrice": 144556.42,
        "sellingValue": 37267.220000000016,
        "profit": 7.7341195288073585,
        "timestamp": 1662685517988,
        "categoriaID": 1,
        "propostaID": "0J14ZCxmEoi5aGsmqEtkOw==",
        "dataRegistro": "2022-09-05T14:39:15.237",
        "valorPago": 107289.2,
        "valorCredito": 481854.72,
        "valorVenda": 144556.42,
        "percentualAgioVenda": 30,
        "dataExpiracao": "2022-10-05T14:39:15.237",
        "parcelasPagas": 48,
        "parcelasRestantes": 192,
        "valorParcela": 2199.84,
        "saldoDevedor": 420952.8,
        "proximoVencimento": "2022-10-08T00:00:00"
    }
}